risk_command_center/__init__.py
risk_command_center/connect.py
risk_command_center/common/__init__.py
risk_command_center/common/huemul_common.py
risk_command_center/common/huemul_connection.py
risk_command_center/common/huemul_datetime_part.py
risk_command_center/common/huemul_error.py
risk_command_center/common/huemul_functions.py
risk_command_center/common/huemul_http_info.py
risk_command_center/common/huemul_logging.py
risk_command_center/common/huemul_param.py
risk_command_center/common/huemul_response_error.py
risk_command_center/common/huemul_response_provider.py
risk_command_center/common/huemul_response_to_bloc.py
risk_command_center/common/auth/__init__.py
risk_command_center/common/auth/auth_model.py
risk_command_center/common/auth/auth_service_bloc.py
risk_command_center/common/auth/auth_service_model.py
risk_command_center/common/auth/auth_service_provider.py
risk_command_center/department/__init__.py
risk_command_center/department/department.py
risk_command_center/internal/__init__.py
risk_command_center/internal/department/__init__.py
risk_command_center/internal/department/department_bloc.py
risk_command_center/internal/department/department_model.py
risk_command_center/internal/department/department_provider.py
risk_command_center/internal/department/department_response_model.py
risk_command_center/internal/risk/__init__.py
risk_command_center/internal/risk/risk_bloc.py
risk_command_center/internal/risk/risk_model.py
risk_command_center/internal/risk/risk_provider.py
risk_command_center/internal/risk/risk_response_model.py
risk_command_center/internal/riskIncident/__init__.py
risk_command_center/internal/riskIncident/riskIncident_bloc.py
risk_command_center/internal/riskIncident/riskIncident_model.py
risk_command_center/internal/riskIncident/riskIncident_provider.py
risk_command_center/internal/riskIncident/riskIncident_response_model.py
risk_command_center/internal/riskIncidentType/__init__.py
risk_command_center-1.0.37.dist-info/LICENSE
risk_command_center-1.0.37.dist-info/METADATA
risk_command_center-1.0.37.dist-info/WHEEL
risk_command_center-1.0.37.dist-info/top_level.txt
risk_command_center-1.0.37.dist-info/RECORD
