Metadata-Version: 2.1
Name: risk-command-center
Version: 1.0.37
Summary: Risk Command Center, manage your risk easly.
Home-page: https://risk-command-center.com
Author: Developer Code HuemulSolutions
Author-email: developer.code@huemulsolutions.com
Project-URL: Bug Tracker, https://github.com/HuemulSolutions/huemul-bigdatagovernance/issues
Classifier: Programming Language :: Python :: 3
Classifier: License :: OSI Approved :: MIT License
Classifier: Operating System :: OS Independent
Requires-Python: >=3.6
License-File: LICENSE
